rivus/__init__.py
rivus/cli.py
rivus-0.0.2.dist-info/METADATA
rivus-0.0.2.dist-info/WHEEL
rivus-0.0.2.dist-info/entry_points.txt
rivus-0.0.2.dist-info/RECORD
