Metadata-Version: 2.4
Name: rivus
Version: 0.0.2
Summary: Rivus: orchestration control plane for portable runs (seed release)
Project-URL: Homepage, https://github.com/your-org/rivus
Project-URL: Repository, https://github.com/your-org/rivus
Project-URL: Documentation, https://your-org.github.io/rivus
Project-URL: Issues, https://github.com/your-org/rivus/issues
Author-email: Your Org <dev@yourorg.com>
License: Proprietary
Classifier: Development Status :: 3 - Alpha
Classifier: Intended Audience :: Developers
Classifier: License :: Other/Proprietary License
Classifier: Programming Language :: Python :: 3
Classifier: Programming Language :: Python :: 3.10
Classifier: Topic :: Software Development :: Build Tools
Requires-Python: >=3.10
